{
    "categories": {
        "일반공지": [
            {
                "subject": "[문학문화콘텐츠트랙] 동일 교과목 목록 (2024-2학기 기준)",
                "write": "크리에이티브인문학부",
                "date": "2024.02.07",
                "link": "https://www.hansung.ac.kr/bbs/HmnArt/56/259007/artclView.do",
                "file": 0
            },
            {
                "subject": "[문학문화콘텐츠트랙] 2트랙 학생 지도교수 현황 안내 (2023-2학기 기준)",
                "write": "크리에이티브인문학부",
                "date": "2023.09.15",
                "link": "https://www.hansung.ac.kr/bbs/HmnArt/56/256832/artclView.do",
                "file": 1
            },
            {
                "subject": "[문학문화콘텐츠트랙 / 국어국문전공] 졸업요건 안내",
                "write": "크리에이티브인문학부",
                "date": "2022.02.17",
                "link": "https://www.hansung.ac.kr/bbs/HmnArt/56/244684/artclView.do",
                "file": 3
            }
        ]
    },
    "notices_by_id": {
        "31": {
            "subject": "[홍보] 성북문화재단 X 지역대학 인문지식프로젝트 개최 안내",
            "write": "문학문화콘텐츠학과",
            "date": "2025.05.08",
            "link": "https://www.hansung.ac.kr/bbs/HmnArt/56/268491/artclView.do",
            "file": 2
        },
        "30": {
            "subject": "[홍보] 삼성 청년 SW·AI 아카데미(SSAFY) 14기 모집 안내",
            "write": "문학문화콘텐츠학과",
            "date": "2025.04.29",
            "link": "https://www.hansung.ac.kr/bbs/HmnArt/56/268373/artclView.do",
            "file": 3
        },
        "29": {
            "subject": "[공모전] #My Holiday Inn 숏폼 콘테스트 개최 안내",
            "write": "문학문화콘텐츠학과",
            "date": "2025.04.28",
            "link": "https://www.hansung.ac.kr/bbs/HmnArt/56/268345/artclView.do",
            "file": 2
        },
        "28": {
            "subject": "[홍보] 너나들이뷰 대학생 대상 뷰플리 친환경 서포터즈 모집 안내",
            "write": "문학문화콘텐츠학과",
            "date": "2025.04.18",
            "link": "https://www.hansung.ac.kr/bbs/HmnArt/56/268130/artclView.do",
            "file": 1
        },
        "27": {
            "subject": "제26회 한국어문학부 장학재단 “특기적성” 장학생 선발 안내(~5.10.)",
            "write": "문학문화콘텐츠학과",
            "date": "2025.04.11",
            "link": "https://www.hansung.ac.kr/bbs/HmnArt/56/267965/artclView.do",
            "file": 1
        },
        "26": {
            "subject": "[공모전]「제12회 오장환 신인문학상 공모전」개최",
            "write": "문학문화콘텐츠학과",
            "date": "2025.04.11",
            "link": "https://www.hansung.ac.kr/bbs/HmnArt/56/267961/artclView.do",
            "file": 1
        },
        "25": {
            "subject": "[문학문화콘텐츠트랙 / 국어국문전공] 2025-1학기 수강정정(서면신청) 안내",
            "write": "크리에이티브인문학부",
            "date": "2025.02.12",
            "link": "https://www.hansung.ac.kr/bbs/HmnArt/56/266599/artclView.do",
            "file": 2
        },
        "24": {
            "subject": "인공지능 활용 콘텐츠 제작 전공 학위 추가 취득 안내",
            "write": "크리에이티브인문학부",
            "date": "2024.12.12",
            "link": "https://www.hansung.ac.kr/bbs/HmnArt/56/265422/artclView.do",
            "file": 1
        },
        "23": {
            "subject": "[문학문화콘텐츠트랙 / 학과] 2024학년도 문화콘텐츠 기획 공모전 결과 발표(수정)",
            "write": "문학문화콘텐츠학과",
            "date": "2024.11.25",
            "link": "https://www.hansung.ac.kr/bbs/HmnArt/56/265055/artclView.do",
            "file": 0
        },
        "22": {
            "subject": "[문학문화콘텐츠전공인의 밤] 문화콘텐츠 기획공모전 개최 공지",
            "write": "크리에이티브인문학부",
            "date": "2024.11.05",
            "link": "https://www.hansung.ac.kr/bbs/HmnArt/56/264709/artclView.do",
            "file": 1
        },
        "21": {
            "subject": "2024-2학기 산업 연계형 HSP 실습프로그램 안내",
            "write": "크리에이티브인문학부",
            "date": "2024.10.15",
            "link": "https://www.hansung.ac.kr/bbs/HmnArt/56/264278/artclView.do",
            "file": 0
        },
        "20": {
            "subject": "제25회 한국어문학부 장학재단 “특기적성” 장학생 선발 안내(~10.13.)",
            "write": "크리에이티브인문학부",
            "date": "2024.09.10",
            "link": "https://www.hansung.ac.kr/bbs/HmnArt/56/263744/artclView.do",
            "file": 1
        },
        "19": {
            "subject": "[문학문화콘텐츠트랙 / 국어국문전공] 2024-2학기 1,2차 수강정정(서면신청) 안내",
            "write": "크리에이티브인문학부",
            "date": "2024.08.14",
            "link": "https://www.hansung.ac.kr/bbs/HmnArt/56/262985/artclView.do",
            "file": 2
        },
        "18": {
            "subject": "2024 EBS 화상튜터링 대학생 멘토 모집(활동 기간 2024년 7월~12월)",
            "write": "문학문화콘텐츠학과",
            "date": "2024.07.03",
            "link": "https://www.hansung.ac.kr/bbs/HmnArt/56/262178/artclView.do",
            "file": 1
        },
        "17": {
            "subject": "꽁꽁 얼어붙은 과제 뽐내기 공모전 (~ 05.29.)",
            "write": "크리에이티브인문학부",
            "date": "2024.05.24",
            "link": "https://www.hansung.ac.kr/bbs/HmnArt/56/261235/artclView.do",
            "file": 1
        },
        "16": {
            "subject": "삼성 청년 SW 아카데미」12기 교육생 모집 (04.22. ~ 05.07.)",
            "write": "크리에이티브인문학부",
            "date": "2024.04.18",
            "link": "https://www.hansung.ac.kr/bbs/HmnArt/56/260452/artclView.do",
            "file": 4
        },
        "15": {
            "subject": "세상의 모든 제테크 2024서울머니쇼 홍보(05.09 ~ 05.11)",
            "write": "크리에이티브인문학부",
            "date": "2024.04.18",
            "link": "https://www.hansung.ac.kr/bbs/HmnArt/56/260451/artclView.do",
            "file": 0
        },
        "14": {
            "subject": "송월타올 리테일 마케팅 부문 신입 사무직 추천채용(~04.21.)",
            "write": "크리에이티브인문학부",
            "date": "2024.04.03",
            "link": "https://www.hansung.ac.kr/bbs/HmnArt/56/260083/artclView.do",
            "file": 3
        },
        "13": {
            "subject": "제 10회 통일모의국무회의 경연대회 안내(04.22. ~ 05.11.)",
            "write": "크리에이티브인문학부",
            "date": "2024.03.20",
            "link": "https://www.hansung.ac.kr/bbs/HmnArt/56/259827/artclView.do",
            "file": 2
        },
        "12": {
            "subject": "[문학문화콘텐츠트랙 / 국어국문전공] 2024-1학기 2차 수강정정(서면신청) 안내",
            "write": "크리에이티브인문학부",
            "date": "2024.02.26",
            "link": "https://www.hansung.ac.kr/bbs/HmnArt/56/259280/artclView.do",
            "file": 2
        },
        "11": {
            "subject": "[문학문화콘텐츠트랙] 동일 교과목 목록 (2024-2학기 기준)",
            "write": "크리에이티브인문학부",
            "date": "2024.02.07",
            "link": "https://www.hansung.ac.kr/bbs/HmnArt/56/259007/artclView.do",
            "file": 0
        },
        "10": {
            "subject": "[문학문화콘텐츠트랙 / 학과] 2023학년도 문화콘텐츠 기획 공모전 신청 안내",
            "write": "크리에이티브인문학부",
            "date": "2023.12.19",
            "link": "https://www.hansung.ac.kr/bbs/HmnArt/56/258251/artclView.do",
            "file": 2
        },
        "9": {
            "subject": "제23회 한국어문학부 장학재단 \"특기적성\" 장학생 선발 안내",
            "write": "크리에이티브인문학부",
            "date": "2023.11.07",
            "link": "https://www.hansung.ac.kr/bbs/HmnArt/56/257656/artclView.do",
            "file": 1
        },
        "8": {
            "subject": "[문학문화콘텐츠트랙] 2023-2 비교과 특강 안내",
            "write": "크리에이티브인문학부",
            "date": "2023.10.30",
            "link": "https://www.hansung.ac.kr/bbs/HmnArt/56/257566/artclView.do",
            "file": 0
        },
        "7": {
            "subject": "[문학문화콘텐츠트랙] 2트랙 학생 지도교수 현황 안내 (2023-2학기 기준)",
            "write": "크리에이티브인문학부",
            "date": "2023.09.15",
            "link": "https://www.hansung.ac.kr/bbs/HmnArt/56/256832/artclView.do",
            "file": 1
        },
        "6": {
            "subject": "[문학문화콘텐츠트랙 / 국어국문전공] 2023-2 2차 수강정정(서면신청) 안내",
            "write": "크리에이티브인문학부",
            "date": "2023.08.14",
            "link": "https://www.hansung.ac.kr/bbs/HmnArt/56/256157/artclView.do",
            "file": 4
        },
        "5": {
            "subject": "[비교과] 웹소설의 이해 4기 모집 안내",
            "write": "국어국문전공",
            "date": "2022.11.28",
            "link": "https://www.hansung.ac.kr/bbs/HmnArt/56/250751/artclView.do",
            "file": 0
        },
        "4": {
            "subject": "[공모전] 알에스미디어 시놉시스 공모전 안내",
            "write": "국어국문전공",
            "date": "2022.11.24",
            "link": "https://www.hansung.ac.kr/bbs/HmnArt/56/250671/artclView.do",
            "file": 0
        },
        "3": {
            "subject": "[문학문화콘텐츠트랙] 2트랙 학생 지도교수 배정 결과 안내",
            "write": "국어국문전공",
            "date": "2022.10.24",
            "link": "https://www.hansung.ac.kr/bbs/HmnArt/56/249803/artclView.do",
            "file": 2
        },
        "2": {
            "subject": "개교 50주년 기념 문학문화콘텐츠 기획·피칭 공모전 변경 일정(1차 심사 합격자 대상 공지 ...",
            "write": "국어국문전공",
            "date": "2022.09.14",
            "link": "https://www.hansung.ac.kr/bbs/HmnArt/56/248926/artclView.do",
            "file": 0
        },
        "1": {
            "subject": "제 21회 한국어문학부 장학재단 \"특기적성\" 장학생 선발 안내",
            "write": "국어국문전공",
            "date": "2022.09.06",
            "link": "https://www.hansung.ac.kr/bbs/HmnArt/56/248788/artclView.do",
            "file": 1
        }
    }
}